repozee/__init__.py
repozee/__main__.py
repozee/ai.py
repozee/command/__init__.py
repozee/command/chat_command.py
repozee/command/commit_command.py
repozee/definitions/commit_from_diff.md
repozee/definitions/system.md
repozee/definitions/tools.yml
repozee/definitions/user.md
repozee/toolset.py
repozee-0.2.1.dist-info/METADATA
repozee-0.2.1.dist-info/WHEEL
repozee-0.2.1.dist-info/entry_points.txt
repozee-0.2.1.dist-info/RECORD
