Metadata-Version: 2.1
Name: repozee
Version: 0.2.1
Summary: Explore the contents of a Git repository in a local filesystem
Home-page: https://steamwiz.io
License: MIT
Author: Steampunk Wizard
Author-email: repozee@steamwiz.io
Requires-Python: >=3.11,<3.12
Classifier: License :: OSI Approved :: MIT License
Classifier: Programming Language :: Python :: 3
Classifier: Programming Language :: Python :: 3.11
Requires-Dist: anthropic (>=0.42.0,<0.43.0)
Requires-Dist: gitignore-parser (>=0.1.11,<0.2.0)
Requires-Dist: jinja2 (>=3.1.5,<4.0.0)
Requires-Dist: requests (>=2.32.3,<3.0.0)
Requires-Dist: wizlib (>=3.1.4,<4.0.0)
Project-URL: Repository, https://gitlab.com/steamwiz/busy
